[
{"title": "Psycho\u00a0", "year": "1960", "duration": "1h 49min", "genre": "Horror", "rating": 8.5, "movie_url": "http://web.archive.org/web/20200714055053/https://www.imdb.com/title/tt0054215/"},
{"title": "The Shawshank Redemption\u00a0", "year": "1994", "duration": "2h 22min", "genre": "Drama", "rating": 9.3, "movie_url": "http://web.archive.org/web/20200714035946/https://www.imdb.com/title/tt0111161/"},
{"title": "Casablanca\u00a0", "year": "1942", "duration": "1h 42min", "genre": "Drama", "rating": 8.5, "movie_url": "http://web.archive.org/web/20200714051627/https://www.imdb.com/title/tt0034583/"},
{"title": "American History X\u00a0", "year": "1998", "duration": "1h 59min", "genre": "Drama", "rating": 8.5, "movie_url": "http://web.archive.org/web/20200714080333/https://www.imdb.com/title/tt0120586/"},
{"title": "The Usual Suspects\u00a0", "year": "1995", "duration": "1h 46min", "genre": "Crime", "rating": 8.5, "movie_url": "http://web.archive.org/web/20200714053116/https://www.imdb.com/title/tt0114814/"},
{"title": "Nuovo Cinema Paradiso\u00a0", "year": "1988", "duration": "2h 35min", "genre": "Drama", "rating": 8.5, "movie_url": "http://web.archive.org/web/20200714170157/https://www.imdb.com/title/tt0095765/"},
{"title": "The Lion King\u00a0", "year": "1994", "duration": "1h 28min", "genre": "Animation", "rating": 8.5, "movie_url": "http://web.archive.org/web/20200716172136/https://www.imdb.com/title/tt0110357/"},
{"title": "Back to the Future\u00a0", "year": "1985", "duration": "1h 56min", "genre": "Adventure", "rating": 8.5, "movie_url": "http://web.archive.org/web/20200714232538/https://www.imdb.com/title/tt0088763/"},
{"title": "Gladiator\u00a0", "year": "2000", "duration": "2h 35min", "genre": "Action", "rating": 8.5, "movie_url": "http://web.archive.org/web/20200715145330/http://www.imdb.com/title/tt0172495/"},
{"title": "Die letzten Gl\u00fchw\u00fcrmchen\u00a0", "year": "1988", "duration": "1h 29min", "genre": "Animation", "rating": 8.5, "movie_url": "http://web.archive.org/web/20200715053537/https://www.imdb.com/title/tt0095327/"},
{"title": "L\u00e9on\u00a0", "year": "1994", "duration": "1h 50min", "genre": "Action", "rating": 8.5, "movie_url": "http://web.archive.org/web/20200715072507/https://www.imdb.com/title/tt0110413/"},
{"title": "The Pianist\u00a0", "year": "2002", "duration": "2h 30min", "genre": "Biography", "rating": 8.5, "movie_url": "http://web.archive.org/web/20200715094805/https://www.imdb.com/title/tt0253474/"},
{"title": "Whiplash\u00a0", "year": "2014", "duration": "1h 46min", "genre": "Drama", "rating": 8.5, "movie_url": "http://web.archive.org/web/20200714080433/https://www.imdb.com/title/tt2582802/"},
{"title": "Once Upon a Time in the West\u00a0", "year": "1968", "duration": "2h 45min", "genre": "Western", "rating": 8.5, "movie_url": "http://web.archive.org/web/20200715151431/https://www.imdb.com/title/tt0064116/"},
{"title": "Joker\u00a0", "year": "2019", "duration": "2h 2min", "genre": "Crime", "rating": 8.5, "movie_url": "http://web.archive.org/web/20200714122119/https://www.imdb.com/title/tt7286456/"},
{"title": "The Intouchables\u00a0", "year": "2011", "duration": "1h 52min", "genre": "Biography", "rating": 8.5, "movie_url": "http://web.archive.org/web/20200714080353/https://www.imdb.com/title/tt1675434/"},
{"title": "Anand\u00a0", "year": "1971", "duration": "2h 2min", "genre": "Drama", "rating": 8.6, "movie_url": "http://web.archive.org/web/20200714090047/https://www.imdb.com/title/tt0066763/"},
{"title": "It's a Wonderful Life\u00a0", "year": "1946", "duration": "2h 10min", "genre": "Drama", "rating": 8.6, "movie_url": "http://web.archive.org/web/20200714055953/https://www.imdb.com/title/tt0038650/"},
{"title": "The Departed\u00a0", "year": "2006", "duration": "2h 31min", "genre": "Crime", "rating": 8.5, "movie_url": "http://web.archive.org/web/20200714052524/https://www.imdb.com/title/tt0407887/"},
{"title": "Star Wars: Episode IV - A New Hope\u00a0", "year": "1977", "duration": "2h 1min", "genre": "Action", "rating": 8.6, "movie_url": "http://web.archive.org/web/20200716171627/https://www.imdb.com/title/tt0076759/"},
{"title": "Seven Samurai\u00a0", "year": "1954", "duration": "3h 27min", "genre": "Action", "rating": 8.6, "movie_url": "http://web.archive.org/web/20200716171253/https://www.imdb.com/title/tt0047478/"},
{"title": "Terminator 2: Judgment Day\u00a0", "year": "1991", "duration": "2h 17min", "genre": "Action", "rating": 8.5, "movie_url": "http://web.archive.org/web/20200712022126/https://www.imdb.com/title/tt0103064/"},
{"title": "The Prestige\u00a0", "year": "2006", "duration": "2h 10min", "genre": "Drama", "rating": 8.5, "movie_url": "http://web.archive.org/web/20200716173241/https://www.imdb.com/title/tt0482571/"},
{"title": "The Silence of the Lambs\u00a0", "year": "1991", "duration": "1h 58min", "genre": "Crime", "rating": 8.6, "movie_url": "http://web.archive.org/web/20200715044236/https://www.imdb.com/title/tt0102926/"},
{"title": "Se7en\u00a0", "year": "1995", "duration": "2h 7min", "genre": "Crime", "rating": 8.6, "movie_url": "http://web.archive.org/web/20200714045927/https://www.imdb.com/title/tt0114369/"},
{"title": "Saving Private Ryan\u00a0", "year": "1998", "duration": "2h 49min", "genre": "Drama", "rating": 8.6, "movie_url": "http://web.archive.org/web/20200714052455/https://www.imdb.com/title/tt0120815/"},
{"title": "Spirited Away\u00a0", "year": "2001", "duration": "2h 5min", "genre": "Animation", "rating": 8.6, "movie_url": "http://web.archive.org/web/20200714045337/https://www.imdb.com/title/tt0245429/"},
{"title": "Interstellar\u00a0", "year": "2014", "duration": "2h 49min", "genre": "Adventure", "rating": 8.6, "movie_url": "http://web.archive.org/web/20200714070245/https://www.imdb.com/title/tt0816692/"},
{"title": "City of God\u00a0", "year": "2002", "duration": "2h 10min", "genre": "Crime", "rating": 8.6, "movie_url": "http://web.archive.org/web/20200714035551/https://www.imdb.com/title/tt0317248/"},
{"title": "La vita \u00e8 bella\u00a0", "year": "1997", "duration": "1h 56min", "genre": "Comedy", "rating": 8.6, "movie_url": "http://web.archive.org/web/20200715094956/https://www.imdb.com/title/tt0118799/"},
{"title": "One Flew Over the Cuckoo's Nest\u00a0", "year": "1975", "duration": "2h 13min", "genre": "Drama", "rating": 8.7, "movie_url": "http://web.archive.org/web/20200714035649/https://www.imdb.com/title/tt0073486/"},
{"title": "Goodfellas\u00a0", "year": "1990", "duration": "2h 26min", "genre": "Biography", "rating": 8.7, "movie_url": "http://web.archive.org/web/20200714135956/https://www.imdb.com/title/tt0099685/"},
{"title": "Star Wars: Episode V - The Empire Strikes Back\u00a0", "year": "1980", "duration": "2h 4min", "genre": "Action", "rating": 8.7, "movie_url": "http://web.archive.org/web/20200714105828/https://www.imdb.com/title/tt0080684/"},
{"title": "Parasite\u00a0", "year": "2019", "duration": "2h 12min", "genre": "Comedy", "rating": 8.6, "movie_url": "http://web.archive.org/web/20200714020315/https://www.imdb.com/title/tt6751668/"},
{"title": "The Matrix\u00a0", "year": "1999", "duration": "2h 16min", "genre": "Action", "rating": 8.7, "movie_url": "http://web.archive.org/web/20200714233133/https://www.imdb.com/title/tt0133093/"},
{"title": "Harakiri\u00a0", "year": "1962", "duration": "2h 13min", "genre": "Action", "rating": 8.7, "movie_url": "http://web.archive.org/web/20200716172056/https://www.imdb.com/title/tt0056058/"},
{"title": "Forrest Gump\u00a0", "year": "1994", "duration": "2h 22min", "genre": "Drama", "rating": 8.8, "movie_url": "http://web.archive.org/web/20200715142550/https://www.imdb.com/title/tt0109830/"},
{"title": "Fight Club\u00a0", "year": "1999", "duration": "2h 19min", "genre": "Drama", "rating": 8.8, "movie_url": "http://web.archive.org/web/20200714080106/https://www.imdb.com/title/tt0137523/"},
{"title": "The Lord of the Rings: The Two Towers\u00a0", "year": "2002", "duration": "2h 59min", "genre": "Adventure", "rating": 8.7, "movie_url": "http://web.archive.org/web/20200715072821/https://www.imdb.com/title/tt0167261/"},
{"title": "The Lord of the Rings: The Fellowship of the Ring\u00a0", "year": "2001", "duration": "2h 58min", "genre": "Action", "rating": 8.8, "movie_url": "http://web.archive.org/web/20200714041023/https://www.imdb.com/title/tt0120737/"},
{"title": "The Green Mile\u00a0", "year": "1999", "duration": "3h 9min", "genre": "Crime", "rating": 8.6, "movie_url": "http://web.archive.org/web/20200714044804/https://www.imdb.com/title/tt0120689/"},
{"title": "Schindler's List\u00a0", "year": "1993", "duration": "3h 15min", "genre": "Biography", "rating": 8.9, "movie_url": "http://web.archive.org/web/20200714062836/https://www.imdb.com/title/tt0108052/"},
{"title": "The Lord of the Rings: The Return of the King\u00a0", "year": "2003", "duration": "3h 21min", "genre": "Adventure", "rating": 8.9, "movie_url": "http://web.archive.org/web/20200714041137/https://www.imdb.com/title/tt0167260/"},
{"title": "Il buono, il brutto, il cattivo\u00a0", "year": "1966", "duration": "2h 41min", "genre": "Western", "rating": 8.8, "movie_url": "http://web.archive.org/web/20200715115111/https://www.imdb.com/title/tt0060196/"},
{"title": "The Godfather: Part II\u00a0", "year": "1974", "duration": "3h 22min", "genre": "Crime", "rating": 9.0, "movie_url": "http://web.archive.org/web/20200714052747/https://www.imdb.com/title/tt0071562/"},
{"title": "12 Angry Men\u00a0", "year": "1957", "duration": "1h 36min", "genre": "Crime", "rating": 8.9, "movie_url": "http://web.archive.org/web/20200714005450/https://www.imdb.com/title/tt0050083/"},
{"title": "Inception\u00a0", "year": "2010", "duration": "2h 28min", "genre": "Action", "rating": 8.8, "movie_url": "http://web.archive.org/web/20200716171027/https://www.imdb.com/title/tt1375666/"},
{"title": "The Godfather\u00a0", "year": "1972", "duration": "2h 55min", "genre": "Crime", "rating": 9.2, "movie_url": "http://web.archive.org/web/20200714035749/https://www.imdb.com/title/tt0068646/"},
{"title": "The Dark Knight\u00a0", "year": "2008", "duration": "2h 32min", "genre": "Action", "rating": 9.0, "movie_url": "http://web.archive.org/web/20200716170540/https://www.imdb.com/title/tt0468569/"},
{"title": "Pulp Fiction\u00a0", "year": "1994", "duration": "2h 34min", "genre": "Crime", "rating": 8.9, "movie_url": "http://web.archive.org/web/20200714035314/https://www.imdb.com/title/tt0110912/"}
]